scheduler_pkg/__init__.py
scheduler_pkg/core.py
scheduler_pkg/run_mode.py
scheduler_pkg/scheduled_plan.py
scheduler_pkg/scheduler.py
dcnr_scheduler-1.0.0.dist-info/METADATA
dcnr_scheduler-1.0.0.dist-info/WHEEL
dcnr_scheduler-1.0.0.dist-info/RECORD
